adit_radis_shared/__init__.py
adit_radis_shared/accounts/__init__.py
adit_radis_shared/accounts/admin.py
adit_radis_shared/accounts/apps.py
adit_radis_shared/accounts/backends.py
adit_radis_shared/accounts/factories.py
adit_radis_shared/accounts/forms.py
adit_radis_shared/accounts/middlewares.py
adit_radis_shared/accounts/migrations/0001_initial.py
adit_radis_shared/accounts/migrations/0002_alter_user_id.py
adit_radis_shared/accounts/migrations/0003_rename_misc_settings_user_preferences.py
adit_radis_shared/accounts/migrations/0004_alter_user_preferences.py
adit_radis_shared/accounts/migrations/0005_institute.py
adit_radis_shared/accounts/migrations/0006_user_active_group.py
adit_radis_shared/accounts/migrations/0007_convert_institutes_to_groups.py
adit_radis_shared/accounts/migrations/0008_remove_institute_users.py
adit_radis_shared/accounts/migrations/0009_delete_institute.py
adit_radis_shared/accounts/migrations/__init__.py
adit_radis_shared/accounts/models.py
adit_radis_shared/accounts/templates/accounts/_active_group_selector.html
adit_radis_shared/accounts/templates/accounts/accounts_layout.html
adit_radis_shared/accounts/templates/accounts/profile.html
adit_radis_shared/accounts/tests/integration/conftest.py
adit_radis_shared/accounts/tests/integration/test_login.py
adit_radis_shared/accounts/tests/test_migrations.py
adit_radis_shared/accounts/urls.py
adit_radis_shared/accounts/views.py
adit_radis_shared/common/__init__.py
adit_radis_shared/common/admin.py
adit_radis_shared/common/apps.py
adit_radis_shared/common/decorators.py
adit_radis_shared/common/factories.py
adit_radis_shared/common/forms.py
adit_radis_shared/common/management/__init__.py
adit_radis_shared/common/management/base/__init__.py
adit_radis_shared/common/management/base/celery_beat.py
adit_radis_shared/common/management/base/celery_worker.py
adit_radis_shared/common/management/base/hard_reset_migrations.py
adit_radis_shared/common/management/base/server_command.py
adit_radis_shared-0.2.1.dist-info/LICENSE
adit_radis_shared-0.2.1.dist-info/METADATA
adit_radis_shared-0.2.1.dist-info/WHEEL
adit_radis_shared-0.2.1.dist-info/RECORD
